installYoura/__init__.py
installyoura-0.1.0.dist-info/METADATA
installyoura-0.1.0.dist-info/WHEEL
installyoura-0.1.0.dist-info/top_level.txt
installyoura-0.1.0.dist-info/RECORD
