Metadata-Version: 2.4
Name: installYoura
Version: 0.1.0
Summary: Simple downloader library by EI3RAB
Author: Abdullah Ali
License: MIT
Requires-Python: >=3.8
